click_config
