Metadata-Version: 1.0
Name: click-config
Version: 1.1
Summary: config parsing helper for click
Home-page: https://github.com/EverythingMe/click-config
Author: Roey Berman
Author-email: roey@everything.me
License: UNKNOWN
Keywords: click,config,yaml,ini,cli
Platform: UNKNOWN
